pyekonlib/Controllers.py
pyekonlib/Frames.py
pyekonlib/Migration.py
pyekonlib/Misc.py
pyekonlib/Server.py
pyekonlib/__init__.py
pyekonlib-0.3.dist-info/LICENSE.txt
pyekonlib-0.3.dist-info/METADATA
pyekonlib-0.3.dist-info/WHEEL
pyekonlib-0.3.dist-info/top_level.txt
pyekonlib-0.3.dist-info/RECORD
