Metadata-Version: 2.1
Name: pyekonlib
Version: 0.3
Summary: Server and client modules for Ekon/Connect/Airconet+
Home-page: https://github.com/hllhll/pyekonlib
Author: Hillel ch.
License: UNKNOWN
Platform: UNKNOWN
Classifier: Programming Language :: Python :: 3
Classifier: License :: OSI Approved :: MIT License
Classifier: Operating System :: OS Independent
Classifier: Development Status :: 3 - Alpha
Classifier: Intended Audience :: Developers
Classifier: Topic :: Communications
Classifier: Topic :: Internet :: Proxy Servers
Classifier: Framework :: AsyncIO
Classifier: License :: OSI Approved :: MIT License
Classifier: Programming Language :: Python :: 3
Classifier: Programming Language :: Python :: 3.8
Requires-Python: >=3.8
